{"resourceType":"Device","id":"eumfh-70-275-1","meta":{"profile":["http://hl7.org/fhir/uv/ips/StructureDefinition/Device-uv-ips"]},"text":{"status":"generated","div":"<div xmlns=\"http://www.w3.org/1999/xhtml\"><p class=\"res-header-id\"><b>Generated Narrative: Device eumfh-70-275-1</b></p><a name=\"eumfh-70-275-1\"> </a><a name=\"hceumfh-70-275-1\"> </a><div style=\"display: inline-block; background-color: #d9e0e7; padding: 6px; margin: 4px; border: 1px solid #8da1b4; border-radius: 5px; line-height: 60%\"><p style=\"margin-bottom: 0px\"/><p style=\"margin-bottom: 0px\">Profile: <a href=\"StructureDefinition-Device-uv-ips.html\">Device (IPS)</a></p></div><p><b>type</b>: <span title=\"Codes:{http://snomed.info/sct 787483001}\">No known device use (situation)</span></p><p><b>patient</b>: <a href=\"Patient-eumfh-39-07.html\">Annelise Black (inject 70-275)</a></p></div>"},"type":{"coding":[{"system":"http://snomed.info/sct","code":"787483001","display":"No known device use (situation)"}]},"patient":{"reference":"Patient/eumfh-39-07","display":"Annelise Black (inject 70-275)"}}